[
    {
        "mainPart":{
            "cols": {
                "sm": "12",
                "md": "6",
                "lg": "4",
                "xl": "4"
            },
            "class": "ml-auto topHeight"
        },
        "label":{
        "text": "借款人",
        "cols": {
            "col": "4"
        }
        },
        "items": [
            {
                "field": "borrower",
                "type": "input",
                "cols": {
                    "col": "3"
                },
                "value": "",
                "filled": "",
                "readonly": ""
            },
            {
                "field": "id",
                "type": "input",
                "cols": {
                    "col": "5"
                },
                "value": "",
                "filled": "",
                "readonly": ""
                
            }
        ]
    },
    {
        "mainPart":{
            "cols": {
                "sm": "12",
                "md": "6",
                "lg": "4",
                "xl": "3"
            }
        },
        "label":{
        "text": "文件亂碼",
        "cols": {
            "col": "6"
        }
        },
        "items": [
            {
                "field": "garbled",
                "type": "input",
                "cols": {
                    "col": "6"
                },
                "value": "",
                "filled": "",
                "readonly": ""
            }
        ]
    },
    {
        "mainPart":{
            "cols": {
                "sm": "12",
                "md": "6",
                "lg": "4",
                "xl": "2"
            }
        },
        "label":{
        "text": "流程狀態",
        "cols": {
            "col": "6"
        }
        },
        "items": [
            {
                "field": "processStatus",
                "type": "input",
                "cols": {
                    "col": "6"
                },
                "value": "",
                "filled": "",
                "readonly": ""
            }
        ]
    },
    {
        "mainPart":{
            "cols": {
                "sm": "12",
                "md": "6",
                "lg": "4",
                "xl": "2"
            }
        },
        "label":{
        "text": "自動退回",
        "cols": {
            "col": "6"
        }
        },
        "items": [
            {
                "field": "autoReturn",
                "type": "input",
                "cols": {
                    "col": "6"
                },
                "value": "",
                "filled": "",
                "readonly": ""
            }
        ]
    }
]